aos_signer/__init__.py
aos_signer/__main__.py
aos_signer/main.py
aos_signer/files/1rootCA.crt
aos_signer/files/__init__.py
aos_signer/files/build_schema.json
aos_signer/files/config.yaml
aos_signer/files/configuration_schema.json
aos_signer/files/publish_schema.json
aos_signer/files/publisher_schema.json
aos_signer/files/root_schema.json
aos_signer/files/state_schema.json
aos_signer/files/__pycache__/__init__.cpython-310.pyc
aos_signer/service_config/__init__.py
aos_signer/service_config/service_configuration.py
aos_signer/service_config/models/__init__.py
aos_signer/service_config/models/build.py
aos_signer/service_config/models/config_chapter.py
aos_signer/service_config/models/configuration.py
aos_signer/service_config/models/publish.py
aos_signer/service_config/models/publisher.py
aos_signer/signer/__init__.py
aos_signer/signer/bootstrapper.py
aos_signer/signer/commands.py
aos_signer/signer/common.py
aos_signer/signer/errors.py
aos_signer/signer/file_details.py
aos_signer/signer/signer.py
aos_signer/signer/uploader.py
aos_signer/signer/user_credentials.py
aos_signer-1.16.0.dist-info/METADATA
aos_signer-1.16.0.dist-info/WHEEL
aos_signer-1.16.0.dist-info/entry_points.txt
aos_signer-1.16.0.dist-info/top_level.txt
aos_signer-1.16.0.dist-info/RECORD
