Metadata-Version: 2.1
Name: aos-signer
Version: 1.16.0
Summary: Aos service manager
Author: EPAM Systems
Author-email: support@aoscloud.io
License: Apache License 2.0
Platform: any
Classifier: Operating System :: OS Independent
Classifier: Programming Language :: Python :: 3
Classifier: Programming Language :: Python :: 3.7
Classifier: Programming Language :: Python :: 3.8
Classifier: Programming Language :: Python :: 3.9
Classifier: Programming Language :: Python :: 3.10
Classifier: Programming Language :: Python :: 3.11
Classifier: Programming Language :: Python :: 3.12
Requires-Python: >=3.7
Requires-Dist: aos-keys (>=1.7.4)
Requires-Dist: ruamel.yaml (>=0.16.10)
Requires-Dist: jsonschema (>=3.2.0)
Requires-Dist: rich (>=10.13)
Requires-Dist: isoduration (>=20.11.0)
Requires-Dist: PyJWT (>=2.6.0)
Requires-Dist: semver (>=3.0.2)
Requires-Dist: importlib-metadata (==4.2.0) ; python_version < "3.8"
Requires-Dist: importlib-resources (>=3.0) ; python_version < "3.9"
